MANIFEST.in
README.md
pyproject.toml
setup.py
wyp/__init__.py
wyp/serve.py
wyp.egg-info/PKG-INFO
wyp.egg-info/SOURCES.txt
wyp.egg-info/dependency_links.txt
wyp.egg-info/entry_points.txt
wyp.egg-info/requires.txt
wyp.egg-info/top_level.txt
wyp/build/favicon.png
wyp/build/index.html
wyp/build/robots.txt
wyp/build/vite-manifest.json
wyp/build/_app/version.json
wyp/build/_app/immutable/start-fb0d86f8.js
wyp/build/_app/immutable/assets/_layout-46556374.css
wyp/build/_app/immutable/assets/_page-94759636.css
wyp/build/_app/immutable/assets/codicon-71cccbf1.ttf
wyp/build/_app/immutable/assets/monaco-96c4ed5a.css
wyp/build/_app/immutable/chunks/0-dca18611.js
wyp/build/_app/immutable/chunks/1-0c93e5c3.js
wyp/build/_app/immutable/chunks/2-7023aa93.js
wyp/build/_app/immutable/chunks/_layout-76b2ab9d.js
wyp/build/_app/immutable/chunks/abap-ffbe9c82.js
wyp/build/_app/immutable/chunks/apex-38989e74.js
wyp/build/_app/immutable/chunks/azcli-714c239b.js
wyp/build/_app/immutable/chunks/bat-7eb152e5.js
wyp/build/_app/immutable/chunks/bicep-80731f71.js
wyp/build/_app/immutable/chunks/cameligo-91a865e0.js
wyp/build/_app/immutable/chunks/clojure-7e0f8eaa.js
wyp/build/_app/immutable/chunks/coffee-af1c6ca9.js
wyp/build/_app/immutable/chunks/cpp-d3907575.js
wyp/build/_app/immutable/chunks/csharp-d087d64c.js
wyp/build/_app/immutable/chunks/csp-13ea92a6.js
wyp/build/_app/immutable/chunks/css-1949305a.js
wyp/build/_app/immutable/chunks/cssMode-81aeb66a.js
wyp/build/_app/immutable/chunks/cypher-e148524e.js
wyp/build/_app/immutable/chunks/dart-0a096fe0.js
wyp/build/_app/immutable/chunks/dockerfile-af4eb422.js
wyp/build/_app/immutable/chunks/ecl-8f5b983c.js
wyp/build/_app/immutable/chunks/editor.main-a2064434.js
wyp/build/_app/immutable/chunks/elixir-2325ed05.js
wyp/build/_app/immutable/chunks/flow9-47a350b0.js
wyp/build/_app/immutable/chunks/freemarker2-9302ac42.js
wyp/build/_app/immutable/chunks/fsharp-de5183ae.js
wyp/build/_app/immutable/chunks/go-a9169306.js
wyp/build/_app/immutable/chunks/graphql-e84c0b6e.js
wyp/build/_app/immutable/chunks/handlebars-49fd3675.js
wyp/build/_app/immutable/chunks/hcl-3a006f6b.js
