Metadata-Version: 2.1
Name: wyp
Version: 0.1.2
Summary: What You Write Is What You Plot
Author: Jean-Baptiste Cordonnier
Project-URL: homepage, https://github.com/jbcdnr/wyp
Project-URL: repository, https://github.com/jbcdnr/wyp
Requires-Python: >=3.8
